micsync/__init__.py
micsync/__main__.py
micsync/backup_mode.py
micsync/configurations.py
micsync/flags.py
micsync/micsync.py
micsync/mode.py
micsync/paths.py
micsync/rsync.py
micsync/transfer_mode.py
micsync/tree_mode.py
micsync/user.py
micsync/version.py
micsync/version_mode.py
micsync/work_mode.py
micsync-0.0.4.dev1.data/scripts/micsync
micsync-0.0.4.dev1.dist-info/LICENSE.txt
micsync-0.0.4.dev1.dist-info/METADATA
micsync-0.0.4.dev1.dist-info/WHEEL
micsync-0.0.4.dev1.dist-info/top_level.txt
micsync-0.0.4.dev1.dist-info/RECORD
