Metadata-Version: 2.1
Name: micsync
Version: 0.0.4.dev1
Summary: Local data synchronization tool based on rsync.
Home-page: https://github.com/micdmy/micsync/
Author: micdmy
Author-email: micdmy2@gmail.com
License: GPLv3
Platform: UNKNOWN
Classifier: Programming Language :: Python :: 3.7
Classifier: Programming Language :: Python :: 3.8
Classifier: License :: OSI Approved :: GNU General Public License v3 (GPLv3)
Classifier: Operating System :: POSIX :: Linux
Requires-Python: >=3.7
